ez_setup.py
pycassaShell
setup.py
pycassa/__init__.py
pycassa/batch.py
pycassa/columnfamily.py
pycassa/columnfamilymap.py
pycassa/connection.py
pycassa/index.py
pycassa/marshal.py
pycassa/pool.py
pycassa/system_manager.py
pycassa/types.py
pycassa/util.py
pycassa.egg-info/PKG-INFO
pycassa.egg-info/SOURCES.txt
pycassa.egg-info/dependency_links.txt
pycassa.egg-info/requires.txt
pycassa.egg-info/top_level.txt
pycassa/cassandra/Cassandra.py
pycassa/cassandra/__init__.py
pycassa/cassandra/constants.py
pycassa/cassandra/ttypes.py
pycassa/contrib/__init__.py
pycassa/contrib/stubs.py
pycassa/logging/__init__.py
pycassa/logging/pool_logger.py
pycassa/logging/pool_stats_logger.py
pycassa/logging/pycassa_logger.py