Metadata-Version: 1.1
Name: pycassa
Version: 1.9.1
Summary: Python client library for Apache Cassandra
Home-page: http://github.com/pycassa/pycassa
Author: Tyler Hobbs
Author-email: pycassa.maintainer@gmail.com
License: UNKNOWN
Keywords: pycassa,cassandra,client,driver,db,distributed,thrift
Platform: UNKNOWN
Classifier: Development Status :: 5 - Production/Stable
Classifier: Intended Audience :: Developers
Classifier: License :: OSI Approved :: MIT License
Classifier: Natural Language :: English
Classifier: Operating System :: OS Independent
Classifier: Programming Language :: Python
Classifier: Programming Language :: Python :: 2
Classifier: Programming Language :: Python :: 2.6
Classifier: Programming Language :: Python :: 2.7
Classifier: Programming Language :: Python :: 2 :: Only
Classifier: Topic :: Software Development :: Libraries :: Python Modules
